brickproof-cli/__init__.py
brickproof-cli/__main__.py
brickproof_cli/__init__.py
brickproof_cli/__main__.py
brickproof_cli-0.0.2.dist-info/METADATA
brickproof_cli-0.0.2.dist-info/WHEEL
brickproof_cli-0.0.2.dist-info/entry_points.txt
brickproof_cli-0.0.2.dist-info/top_level.txt
brickproof_cli-0.0.2.dist-info/RECORD
